GloriousProtonManager/__init__.py
GloriousProtonManager/__main__.py
GloriousProtonManager/constants.py
GloriousProtonManager/functions.py
GloriousProtonManager/interface.py
GloriousProtonManager-0.90.3.dist-info/LICENSE
GloriousProtonManager-0.90.3.dist-info/METADATA
GloriousProtonManager-0.90.3.dist-info/WHEEL
GloriousProtonManager-0.90.3.dist-info/entry_points.txt
GloriousProtonManager-0.90.3.dist-info/top_level.txt
GloriousProtonManager-0.90.3.dist-info/RECORD
