Metadata-Version: 2.1
Name: GloriousProtonManager
Version: 0.90.3
Summary: Manage Proton-GE from a simple UI
Home-page: https://github.com/thelocomotion/GloriousProtonManager
Author: CDT
Author-email: thelocomotionnn@gmail.com
License: GNU General Public License v3 (GPLv3)
Keywords: proton proton-ge wine linux valve
Classifier: Programming Language :: Python :: 3
Requires-Python: >=3.10
License-File: LICENSE
Requires-Dist: PySimpleGUI
Requires-Dist: requests
